lisvap1.py
lisflood_lisvap-0.4.2.data/scripts/lisvap
lisvap/__init__.py
lisvap/lisvapdynamic.py
lisvap/lisvapinitial.py
lisvap/hydrological/__init__.py
lisvap/hydrological/miscinitial.py
lisvap/hydrological/readmeteo.py
lisvap/utils/__init__.py
lisvap/utils/decorators.py
lisvap/utils/defaults_options.py
lisvap/utils/operators.py
lisvap/utils/output.py
lisvap/utils/readers.py
lisvap/utils/tools.py
lisvap/utils/writers.py
lisflood_lisvap-0.4.2.dist-info/LICENSE
lisflood_lisvap-0.4.2.dist-info/METADATA
lisflood_lisvap-0.4.2.dist-info/WHEEL
lisflood_lisvap-0.4.2.dist-info/top_level.txt
lisflood_lisvap-0.4.2.dist-info/zip-safe
lisflood_lisvap-0.4.2.dist-info/RECORD
