Metadata-Version: 2.1
Name: lisflood-lisvap
Version: 0.4.2
Summary: LISVAP model python module
Home-page: https://github.com/ec-jrc/lisflood-lisvap
Author: Ad de Roo, Peter Burek, Johan van der Knijff, Domenico Nappo
Author-email: domenico.nappo@ext.ec.europa.eu
License: EUPL 1.2
Keywords: lisflood lisvap efas evapotranspiration evaporation
Platform: UNKNOWN
Classifier: Development Status :: 4 - Beta
Classifier: Intended Audience :: Developers
Classifier: Intended Audience :: Education
Classifier: Intended Audience :: Financial and Insurance Industry
Classifier: Intended Audience :: Other Audience
Classifier: Intended Audience :: Science/Research
Classifier: License :: OSI Approved :: European Union Public Licence 1.2 (EUPL 1.2)
Classifier: Operating System :: Unix
Classifier: Operating System :: POSIX
Classifier: Operating System :: Microsoft :: Windows
Classifier: Operating System :: MacOS :: MacOS X
Classifier: Programming Language :: Python
Classifier: Programming Language :: Python :: 2.7
Classifier: Programming Language :: Python :: 3
Classifier: Programming Language :: Python :: 3.5
Classifier: Programming Language :: Python :: 3.6
Classifier: Programming Language :: Python :: 3.7
Classifier: Programming Language :: Python :: Implementation :: CPython
Classifier: Topic :: Scientific/Engineering :: Physics
Requires-Python: >=2.7,!=3.0.*,!=3.1.*
Requires-Dist: numpy (>=1.15)
Requires-Dist: netCDF4
Requires-Dist: python-dateutil
Requires-Dist: future
Requires-Dist: nine
Requires-Dist: pathlib2
